percentify/__init__.py
percentify/core.py
percentify-0.1.4.dist-info/licenses/LICENSE
percentify-0.1.4.dist-info/METADATA
percentify-0.1.4.dist-info/WHEEL
percentify-0.1.4.dist-info/top_level.txt
percentify-0.1.4.dist-info/RECORD
