Metadata-Version: 2.4
Name: percentify
Version: 0.1.4
Summary: A micro-library to easily calculate percentage between two numbers.
Author-email: Daniel Emakporuena <danielemakporuena1@gmail.com>
License: Apache-2.0
Classifier: Programming Language :: Python :: 3
Classifier: License :: OSI Approved :: Apache Software License
Classifier: Operating System :: OS Independent
Requires-Python: >=3.7
License-File: LICENSE
Dynamic: license-file
